[
    {
        "rating": 3,
        "comment": "",
        "idprogram": "https://www.metacritic.com/tv/24",
        "whencreated": "Fri, 06 Nov 2020 20:46:32 GMT",
        "whenmodified": "Fri, 06 Nov 2020 20:46:32 GMT"
    },
    {
        "rating": 1,
        "comment": "",
        "idprogram": "https://www.metacritic.com/tv/666-park-avenue",
        "whencreated": "Tue, 15 Dec 2020 12:08:31 GMT",
        "whenmodified": "Tue, 15 Dec 2020 12:08:31 GMT"
    },
    {
        "rating": 2,
        "comment": "",
        "idprogram": "https://www.metacritic.com/tv/a-discovery-of-witches",
        "whencreated": "Thu, 19 Nov 2020 15:30:10 GMT",
        "whenmodified": "Thu, 19 Nov 2020 15:30:10 GMT"
    },
    {
        "rating": 2,
        "comment": "",
        "idprogram": "https://www.metacritic.com/tv/agents-of-chaos",
        "whencreated": "Tue, 05 Jan 2021 09:54:35 GMT",
        "whenmodified": "Tue, 05 Jan 2021 09:54:35 GMT"
    },
    {
        "rating": 1,
        "comment": "",
        "idprogram": "https://www.metacritic.com/tv/alcatraz",
        "whencreated": "Sun, 08 Nov 2020 17:42:15 GMT",
        "whenmodified": "Sun, 08 Nov 2020 17:42:15 GMT"
    },
    {
        "rating": 2,
        "comment": "",
        "idprogram": "https://www.metacritic.com/tv/alphas",
        "whencreated": "Sun, 08 Nov 2020 17:41:47 GMT",
        "whenmodified": "Sun, 08 Nov 2020 17:41:47 GMT"
    },
    {
        "rating": 2,
        "comment": "",
        "idprogram": "https://www.metacritic.com/tv/american-gods",
        "whencreated": "Fri, 06 Nov 2020 20:47:38 GMT",
        "whenmodified": "Fri, 06 Nov 2020 20:47:38 GMT"
    },
    {
        "rating": 2,
        "comment": "",
        "idprogram": "https://www.metacritic.com/tv/american-gothic",
        "whencreated": "Fri, 06 Nov 2020 21:17:17 GMT",
        "whenmodified": "Fri, 06 Nov 2020 21:17:17 GMT"
    },
    {
        "rating": 2,
        "comment": "",
        "idprogram": "https://www.metacritic.com/tv/american-horror-story",
        "whencreated": "Fri, 06 Nov 2020 20:46:28 GMT",
        "whenmodified": "Fri, 06 Nov 2020 20:46:28 GMT"
    },
    {
        "rating": 3,
        "comment": "",
        "idprogram": "https://www.metacritic.com/tv/angel",
        "whencreated": "Fri, 06 Nov 2020 20:58:56 GMT",
        "whenmodified": "Fri, 06 Nov 2020 20:58:56 GMT"
    },
    {
        "rating": 3,
        "comment": "",
        "idprogram": "https://www.metacritic.com/tv/arrow",
        "whencreated": "Fri, 06 Nov 2020 20:46:24 GMT",
        "whenmodified": "Fri, 06 Nov 2020 20:46:24 GMT"
    },
    {
        "rating": 2,
        "comment": "",
        "idprogram": "https://www.metacritic.com/tv/ashes-to-ashes",
        "whencreated": "Sun, 08 Nov 2020 17:55:06 GMT",
        "whenmodified": "Sun, 08 Nov 2020 17:55:06 GMT"
    },
    {
        "rating": 3,
        "comment": "",
        "idprogram": "https://www.metacritic.com/tv/babylon-5",
        "whencreated": "Fri, 06 Nov 2020 20:42:01 GMT",
        "whenmodified": "Fri, 06 Nov 2020 20:42:01 GMT"
    },
    {
        "rating": 3,
        "comment": "",
        "idprogram": "https://www.metacritic.com/tv/battlestar-galactica-2003",
        "whencreated": "Fri, 06 Nov 2020 20:46:08 GMT",
        "whenmodified": "Fri, 07 May 2021 10:23:49 GMT"
    },
    {
        "rating": 1,
        "comment": "",
        "idprogram": "https://www.metacritic.com/tv/batwoman",
        "whencreated": "Sat, 07 Nov 2020 00:00:00 GMT",
        "whenmodified": "Sat, 07 Nov 2020 00:00:00 GMT"
    },
    {
        "rating": 1,
        "comment": "",
        "idprogram": "https://www.metacritic.com/tv/bedlam",
        "whencreated": "Tue, 15 Dec 2020 12:08:05 GMT",
        "whenmodified": "Tue, 15 Dec 2020 12:08:05 GMT"
    },
    {
        "rating": 2,
        "comment": "",
        "idprogram": "https://www.metacritic.com/tv/black-narcissus",
        "whencreated": "Fri, 01 Jan 2021 20:28:29 GMT",
        "whenmodified": "Fri, 01 Jan 2021 20:28:29 GMT"
    },
    {
        "rating": 2,
        "comment": "",
        "idprogram": "https://www.metacritic.com/tv/black-sails",
        "whencreated": "Fri, 06 Nov 2020 20:42:25 GMT",
        "whenmodified": "Fri, 06 Nov 2020 20:42:25 GMT"
    },
    {
        "rating": 1,
        "comment": "",
        "idprogram": "https://www.metacritic.com/tv/blade",
        "whencreated": "Thu, 14 Jan 2021 14:56:09 GMT",
        "whenmodified": "Thu, 14 Jan 2021 14:56:09 GMT"
    },
    {
        "rating": 2,
        "comment": "",
        "idprogram": "https://www.metacritic.com/tv/blindspot",
        "whencreated": "Mon, 23 Nov 2020 23:01:18 GMT",
        "whenmodified": "Mon, 23 Nov 2020 23:01:18 GMT"
    },
    {
        "rating": 1,
        "comment": "",
        "idprogram": "https://www.metacritic.com/tv/blood-treasure",
        "whencreated": "Thu, 19 Nov 2020 15:23:50 GMT",
        "whenmodified": "Thu, 19 Nov 2020 15:23:50 GMT"
    },
    {
        "rating": 2,
        "comment": "",
        "idprogram": "https://www.metacritic.com/tv/bloodlands",
        "whencreated": "Sun, 21 Mar 2021 23:13:11 GMT",
        "whenmodified": "Sun, 21 Mar 2021 23:13:11 GMT"
    },
    {
        "rating": 1,
        "comment": "",
        "idprogram": "https://www.metacritic.com/tv/bonekickers",
        "whencreated": "Thu, 19 Nov 2020 15:48:38 GMT",
        "whenmodified": "Thu, 19 Nov 2020 15:48:38 GMT"
    },
    {
        "rating": 3,
        "comment": "",
        "idprogram": "https://www.metacritic.com/tv/bones",
        "whencreated": "Fri, 06 Nov 2020 23:33:22 GMT",
        "whenmodified": "Fri, 06 Nov 2020 23:33:22 GMT"
    },
    {
        "rating": 2,
        "comment": "",
        "idprogram": "https://www.metacritic.com/tv/brave-new-world",
        "whencreated": "Fri, 06 Nov 2020 21:19:11 GMT",
        "whenmodified": "Fri, 06 Nov 2020 21:19:11 GMT"
    },
    {
        "rating": 2,
        "comment": "",
        "idprogram": "https://www.metacritic.com/tv/breaking-bad",
        "whencreated": "Fri, 06 Nov 2020 20:46:48 GMT",
        "whenmodified": "Fri, 06 Nov 2020 20:46:48 GMT"
    },
    {
        "rating": 2,
        "comment": "",
        "idprogram": "https://www.metacritic.com/tv/briarpatch",
        "whencreated": "Fri, 29 Jan 2021 23:21:48 GMT",
        "whenmodified": "Fri, 29 Jan 2021 23:21:48 GMT"
    },
    {
        "rating": 3,
        "comment": "",
        "idprogram": "https://www.metacritic.com/tv/buffy-the-vampire-slayer",
        "whencreated": "Fri, 06 Nov 2020 20:46:03 GMT",
        "whenmodified": "Fri, 06 Nov 2020 20:46:03 GMT"
    },
    {
        "rating": 3,
        "comment": "",
        "idprogram": "https://www.metacritic.com/tv/burn-notice",
        "whencreated": "Fri, 06 Nov 2020 20:43:49 GMT",
        "whenmodified": "Fri, 20 Nov 2020 09:59:48 GMT"
    },
    {
        "rating": 1,
        "comment": "",
        "idprogram": "https://www.metacritic.com/tv/californication",
        "whencreated": "Fri, 06 Nov 2020 20:43:54 GMT",
        "whenmodified": "Fri, 06 Nov 2020 20:43:54 GMT"
    },
    {
        "rating": 1,
        "comment": "",
        "idprogram": "https://www.metacritic.com/tv/camelot",
        "whencreated": "Tue, 10 Nov 2020 17:24:53 GMT",
        "whenmodified": "Tue, 10 Nov 2020 17:24:53 GMT"
    },
    {
        "rating": 3,
        "comment": "",
        "idprogram": "https://www.metacritic.com/tv/cb-strike",
        "whencreated": "Fri, 06 Nov 2020 23:27:19 GMT",
        "whenmodified": "Fri, 06 Nov 2020 23:27:19 GMT"
    },
    {
        "rating": 2,
        "comment": "",
        "idprogram": "https://www.metacritic.com/tv/childhoods-end",
        "whencreated": "Fri, 18 Dec 2020 11:06:23 GMT",
        "whenmodified": "Fri, 18 Dec 2020 11:06:23 GMT"
    },
    {
        "rating": 2,
        "comment": "",
        "idprogram": "https://www.metacritic.com/tv/clarice",
        "whencreated": "Mon, 10 Jan 2022 12:00:07 GMT",
        "whenmodified": "Mon, 10 Jan 2022 12:00:07 GMT"
    },
    {
        "rating": 2,
        "comment": "",
        "idprogram": "https://www.metacritic.com/tv/cleverman",
        "whencreated": "Mon, 23 Nov 2020 23:00:42 GMT",
        "whenmodified": "Mon, 23 Nov 2020 23:00:42 GMT"
    },
    {
        "rating": 1,
        "comment": "",
        "idprogram": "https://www.metacritic.com/tv/colony",
        "whencreated": "Fri, 06 Nov 2020 23:40:41 GMT",
        "whenmodified": "Fri, 06 Nov 2020 23:40:41 GMT"
    },
    {
        "rating": 2,
        "comment": "",
        "idprogram": "https://www.metacritic.com/tv/constantine-2014",
        "whencreated": "Wed, 02 Dec 2020 22:57:44 GMT",
        "whenmodified": "Wed, 02 Dec 2020 22:57:44 GMT"
    },
    {
        "rating": 2,
        "comment": "",
        "idprogram": "https://www.metacritic.com/tv/continuum-2012",
        "whencreated": "Fri, 06 Nov 2020 20:58:18 GMT",
        "whenmodified": "Sun, 08 Nov 2020 17:51:55 GMT"
    },
    {
        "rating": 3,
        "comment": "",
        "idprogram": "https://www.metacritic.com/tv/copper",
        "whencreated": "Sun, 22 Nov 2020 14:24:17 GMT",
        "whenmodified": "Sun, 22 Nov 2020 14:24:17 GMT"
    },
    {
        "rating": 3,
        "comment": "",
        "idprogram": "https://www.metacritic.com/tv/counterpart",
        "whencreated": "Mon, 10 Jan 2022 11:59:07 GMT",
        "whenmodified": "Sun, 13 Feb 2022 15:08:52 GMT"
    },
    {
        "rating": 1,
        "comment": "",
        "idprogram": "https://www.metacritic.com/tv/curfew",
        "whencreated": "Thu, 19 Nov 2020 15:32:06 GMT",
        "whenmodified": "Thu, 19 Nov 2020 15:32:06 GMT"
    },
    {
        "rating": 2,
        "comment": "",
        "idprogram": "https://www.metacritic.com/tv/dan-browns-the-lost-symbol",
        "whencreated": "Sun, 19 Dec 2021 17:45:58 GMT",
        "whenmodified": "Sun, 19 Dec 2021 17:45:58 GMT"
    },
    {
        "rating": 2,
        "comment": "",
        "idprogram": "https://www.metacritic.com/tv/deadly-class",
        "whencreated": "Sun, 21 Mar 2021 23:11:31 GMT",
        "whenmodified": "Sun, 21 Mar 2021 23:11:31 GMT"
    },
    {
        "rating": 3,
        "comment": "",
        "idprogram": "https://www.metacritic.com/tv/devs",
        "whencreated": "Fri, 06 Nov 2020 20:48:40 GMT",
        "whenmodified": "Fri, 06 Nov 2020 20:48:40 GMT"
    },
    {
        "rating": 2,
        "comment": "",
        "idprogram": "https://www.metacritic.com/tv/dexter",
        "whencreated": "Fri, 06 Nov 2020 20:48:43 GMT",
        "whenmodified": "Fri, 06 Nov 2020 20:48:43 GMT"
    },
    {
        "rating": 2,
        "comment": "",
        "idprogram": "https://www.metacritic.com/tv/doctor-who",
        "whencreated": "Fri, 06 Nov 2020 20:49:06 GMT",
        "whenmodified": "Fri, 06 Nov 2020 20:49:06 GMT"
    },
    {
        "rating": 2,
        "comment": "",
        "idprogram": "https://www.metacritic.com/tv/dollhouse",
        "whencreated": "Fri, 06 Nov 2020 20:59:14 GMT",
        "whenmodified": "Fri, 06 Nov 2020 20:59:14 GMT"
    },
    {
        "rating": 2,
        "comment": "",
        "idprogram": "https://www.metacritic.com/tv/emergence",
        "whencreated": "Fri, 06 Nov 2020 21:24:45 GMT",
        "whenmodified": "Fri, 06 Nov 2020 21:24:45 GMT"
    },
    {
        "rating": 3,
        "comment": "",
        "idprogram": "https://www.metacritic.com/tv/eureka",
        "whencreated": "Fri, 06 Nov 2020 20:45:45 GMT",
        "whenmodified": "Fri, 06 Nov 2020 20:45:45 GMT"
    },
    {
        "rating": 2,
        "comment": "",
        "idprogram": "https://www.metacritic.com/tv/evil",
        "whencreated": "Fri, 06 Nov 2020 20:45:52 GMT",
        "whenmodified": "Fri, 06 Nov 2020 20:45:52 GMT"
    },
    {
        "rating": 3,
        "comment": "",
        "idprogram": "https://www.metacritic.com/tv/exterminate-all-the-brutes",
        "whencreated": "Fri, 07 May 2021 10:36:26 GMT",
        "whenmodified": "Fri, 07 May 2021 10:36:26 GMT"
    },
    {
        "rating": 3,
        "comment": "",
        "idprogram": "https://www.metacritic.com/tv/fargo",
        "whencreated": "Fri, 06 Nov 2020 20:49:17 GMT",
        "whenmodified": "Fri, 06 Nov 2020 20:49:17 GMT"
    },
    {
        "rating": 1,
        "comment": "",
        "idprogram": "https://www.metacritic.com/tv/fear-the-walking-dead",
        "whencreated": "Tue, 10 Nov 2020 17:20:27 GMT",
        "whenmodified": "Tue, 10 Nov 2020 17:20:27 GMT"
    },
    {
        "rating": 3,
        "comment": "",
        "idprogram": "https://www.metacritic.com/tv/firefly",
        "whencreated": "Fri, 06 Nov 2020 20:45:57 GMT",
        "whenmodified": "Fri, 06 Nov 2020 20:45:57 GMT"
    },
    {
        "rating": 2,
        "comment": "",
        "idprogram": "https://www.metacritic.com/tv/fortitude",
        "whencreated": "Sat, 12 Mar 2022 15:36:03 GMT",
        "whenmodified": "Sat, 12 Mar 2022 15:36:03 GMT"
    },
    {
        "rating": 2,
        "comment": "",
        "idprogram": "https://www.metacritic.com/tv/fringe",
        "whencreated": "Tue, 15 Dec 2020 11:56:08 GMT",
        "whenmodified": "Tue, 15 Dec 2020 11:56:08 GMT"
    },
    {
        "rating": 2,
        "comment": "",
        "idprogram": "https://www.metacritic.com/tv/from",
        "whencreated": "Wed, 03 Aug 2022 09:48:27 GMT",
        "whenmodified": "Wed, 03 Aug 2022 09:48:27 GMT"
    },
    {
        "rating": 2,
        "comment": "",
        "idprogram": "https://www.metacritic.com/tv/from-dusk-till-dawn-the-series",
        "whencreated": "Wed, 06 Jan 2021 18:42:43 GMT",
        "whenmodified": "Wed, 06 Jan 2021 18:42:43 GMT"
    },
    {
        "rating": 3,
        "comment": "",
        "idprogram": "https://www.metacritic.com/tv/futurama",
        "whencreated": "Fri, 06 Nov 2020 20:49:25 GMT",
        "whenmodified": "Fri, 06 Nov 2020 20:49:25 GMT"
    },
    {
        "rating": 2,
        "comment": "",
        "idprogram": "https://www.metacritic.com/tv/good-omens",
        "whencreated": "Fri, 06 Nov 2020 20:49:33 GMT",
        "whenmodified": "Fri, 06 Nov 2020 20:49:33 GMT"
    },
    {
        "rating": 2,
        "comment": "",
        "idprogram": "https://www.metacritic.com/tv/gotham",
        "whencreated": "Fri, 06 Nov 2020 20:49:38 GMT",
        "whenmodified": "Fri, 06 Nov 2020 20:49:38 GMT"
    },
    {
        "rating": 3,
        "comment": "",
        "idprogram": "https://www.metacritic.com/tv/grimm",
        "whencreated": "Fri, 06 Nov 2020 20:49:43 GMT",
        "whenmodified": "Fri, 06 Nov 2020 20:49:43 GMT"
    },
    {
        "rating": 2,
        "comment": "",
        "idprogram": "https://www.metacritic.com/tv/halo",
        "whencreated": "Wed, 03 Aug 2022 09:49:29 GMT",
        "whenmodified": "Wed, 03 Aug 2022 09:49:29 GMT"
    },
    {
        "rating": 3,
        "comment": "",
        "idprogram": "https://www.metacritic.com/tv/hannibal",
        "whencreated": "Fri, 06 Nov 2020 20:49:46 GMT",
        "whenmodified": "Fri, 06 Nov 2020 20:49:46 GMT"
    },
    {
        "rating": 2,
        "comment": "",
        "idprogram": "https://www.metacritic.com/tv/hard-sun",
        "whencreated": "Sat, 07 Nov 2020 00:11:32 GMT",
        "whenmodified": "Sat, 07 Nov 2020 00:11:32 GMT"
    },
    {
        "rating": 3,
        "comment": "",
        "idprogram": "https://www.metacritic.com/tv/harley-quinn",
        "whencreated": "Sat, 07 Nov 2020 00:00:24 GMT",
        "whenmodified": "Sat, 07 Nov 2020 00:00:24 GMT"
    },
    {
        "rating": 3,
        "comment": "",
        "idprogram": "https://www.metacritic.com/tv/harpers-island",
        "whencreated": "Fri, 06 Nov 2020 21:35:57 GMT",
        "whenmodified": "Fri, 06 Nov 2020 21:35:57 GMT"
    },
    {
        "rating": 2,
        "comment": "",
        "idprogram": "https://www.metacritic.com/tv/haven",
        "whencreated": "Tue, 10 Nov 2020 17:22:38 GMT",
        "whenmodified": "Tue, 10 Nov 2020 17:22:38 GMT"
    },
    {
        "rating": 2,
        "comment": "",
        "idprogram": "https://www.metacritic.com/tv/heroes",
        "whencreated": "Fri, 06 Nov 2020 20:49:51 GMT",
        "whenmodified": "Fri, 06 Nov 2020 20:49:51 GMT"
    },
    {
        "rating": 1,
        "comment": "",
        "idprogram": "https://www.metacritic.com/tv/heroes-reborn",
        "whencreated": "Tue, 15 Dec 2020 11:57:09 GMT",
        "whenmodified": "Tue, 15 Dec 2020 11:57:09 GMT"
    },
    {
        "rating": 2,
        "comment": "",
        "idprogram": "https://www.metacritic.com/tv/his-dark-materials",
        "whencreated": "Fri, 13 Nov 2020 18:02:25 GMT",
        "whenmodified": "Fri, 13 Nov 2020 18:02:25 GMT"
    },
    {
        "rating": 1,
        "comment": "",
        "idprogram": "https://www.metacritic.com/tv/homeland",
        "whencreated": "Fri, 06 Nov 2020 20:49:55 GMT",
        "whenmodified": "Fri, 06 Nov 2020 20:49:55 GMT"
    },
    {
        "rating": 1,
        "comment": "",
        "idprogram": "https://www.metacritic.com/tv/hooten-the-lady",
        "whencreated": "Mon, 23 Nov 2020 20:18:12 GMT",
        "whenmodified": "Mon, 23 Nov 2020 20:18:12 GMT"
    },
    {
        "rating": 3,
        "comment": "",
        "idprogram": "https://www.metacritic.com/tv/house",
        "whencreated": "Fri, 07 May 2021 10:27:15 GMT",
        "whenmodified": "Fri, 07 May 2021 10:27:15 GMT"
    },
    {
        "rating": 3,
        "comment": "",
        "idprogram": "https://www.metacritic.com/tv/humans",
        "whencreated": "Fri, 06 Nov 2020 20:50:14 GMT",
        "whenmodified": "Fri, 06 Nov 2020 20:50:14 GMT"
    },
    {
        "rating": 2,
        "comment": "",
        "idprogram": "https://www.metacritic.com/tv/hustle",
        "whencreated": "Wed, 11 Nov 2020 12:08:21 GMT",
        "whenmodified": "Wed, 11 Nov 2020 12:08:21 GMT"
    },
    {
        "rating": 2,
        "comment": "",
        "idprogram": "https://www.metacritic.com/tv/ice-road-truckers",
        "whencreated": "Tue, 06 Apr 2021 15:09:39 GMT",
        "whenmodified": "Tue, 06 Apr 2021 15:09:39 GMT"
    },
    {
        "rating": 4,
        "comment": "",
        "idprogram": "https://www.metacritic.com/tv/ill-be-gone-in-the-dark",
        "whencreated": "Fri, 06 Nov 2020 20:50:17 GMT",
        "whenmodified": "Fri, 06 Nov 2020 20:50:17 GMT"
    },
    {
        "rating": 2,
        "comment": "",
        "idprogram": "https://www.metacritic.com/tv/instinct",
        "whencreated": "Tue, 08 Dec 2020 10:21:38 GMT",
        "whenmodified": "Tue, 08 Dec 2020 10:21:38 GMT"
    },
    {
        "rating": 2,
        "comment": "",
        "idprogram": "https://www.metacritic.com/tv/jericho",
        "whencreated": "Fri, 06 Nov 2020 20:50:34 GMT",
        "whenmodified": "Fri, 06 Nov 2020 20:50:34 GMT"
    },
    {
        "rating": 3,
        "comment": "",
        "idprogram": "https://www.metacritic.com/tv/justified",
        "whencreated": "Fri, 06 Nov 2020 20:50:40 GMT",
        "whenmodified": "Fri, 06 Nov 2020 20:50:40 GMT"
    },
    {
        "rating": 2,
        "comment": "",
        "idprogram": "https://www.metacritic.com/tv/killing-eve",
        "whencreated": "Fri, 06 Nov 2020 20:50:42 GMT",
        "whenmodified": "Fri, 06 Nov 2020 20:50:42 GMT"
    },
    {
        "rating": 1,
        "comment": "",
        "idprogram": "https://www.metacritic.com/tv/knightfall",
        "whencreated": "Sun, 08 Nov 2020 17:47:44 GMT",
        "whenmodified": "Sun, 08 Nov 2020 17:47:44 GMT"
    },
    {
        "rating": 3,
        "comment": "",
        "idprogram": "https://www.metacritic.com/tv/legion",
        "whencreated": "Fri, 06 Nov 2020 20:50:49 GMT",
        "whenmodified": "Fri, 06 Nov 2020 20:50:49 GMT"
    },
    {
        "rating": 2,
        "comment": "",
        "idprogram": "https://www.metacritic.com/tv/life-on-mars-uk",
        "whencreated": "Sun, 08 Nov 2020 17:54:30 GMT",
        "whenmodified": "Sun, 08 Nov 2020 17:54:30 GMT"
    },
    {
        "rating": 2,
        "comment": "",
        "idprogram": "https://www.metacritic.com/tv/limetown",
        "whencreated": "Thu, 18 Nov 2021 19:33:29 GMT",
        "whenmodified": "Thu, 18 Nov 2021 19:33:29 GMT"
    },
    {
        "rating": 1,
        "comment": "",
        "idprogram": "https://www.metacritic.com/tv/lincoln-rhyme-hunt-for-the-bone-collector",
        "whencreated": "Fri, 01 Jan 2021 20:24:13 GMT",
        "whenmodified": "Fri, 01 Jan 2021 20:24:13 GMT"
    },
    {
        "rating": 2,
        "comment": "",
        "idprogram": "https://www.metacritic.com/tv/lost",
        "whencreated": "Fri, 06 Nov 2020 20:50:59 GMT",
        "whenmodified": "Fri, 06 Nov 2020 20:50:59 GMT"
    },
    {
        "rating": 2,
        "comment": "",
        "idprogram": "https://www.metacritic.com/tv/lovecraft-country",
        "whencreated": "Tue, 10 Jan 2023 22:36:23 GMT",
        "whenmodified": "Tue, 10 Jan 2023 22:36:23 GMT"
    },
    {
        "rating": 2,
        "comment": "",
        "idprogram": "https://www.metacritic.com/tv/lucifer",
        "whencreated": "Wed, 24 Aug 2022 22:43:07 GMT",
        "whenmodified": "Wed, 24 Aug 2022 22:43:07 GMT"
    },
    {
        "rating": 3,
        "comment": "",
        "idprogram": "https://www.metacritic.com/tv/luther",
        "whencreated": "Fri, 06 Nov 2020 20:51:10 GMT",
        "whenmodified": "Fri, 06 Nov 2020 20:51:10 GMT"
    },
    {
        "rating": 2,
        "comment": "",
        "idprogram": "https://www.metacritic.com/tv/manifest",
        "whencreated": "Fri, 16 Sep 2022 11:10:06 GMT",
        "whenmodified": "Fri, 16 Sep 2022 11:10:22 GMT"
    },
    {
        "rating": 3,
        "comment": "",
        "idprogram": "https://www.metacritic.com/tv/marvels-agent-carter",
        "whencreated": "Fri, 06 Nov 2020 20:51:20 GMT",
        "whenmodified": "Fri, 06 Nov 2020 20:51:20 GMT"
    },
    {
        "rating": 3,
        "comment": "",
        "idprogram": "https://www.metacritic.com/tv/marvels-agents-of-shield",
        "whencreated": "Fri, 06 Nov 2020 20:51:22 GMT",
        "whenmodified": "Fri, 06 Nov 2020 20:51:22 GMT"
    },
    {
        "rating": 1,
        "comment": "",
        "idprogram": "https://www.metacritic.com/tv/marvels-inhumans",
        "whencreated": "Fri, 06 Nov 2020 20:51:23 GMT",
        "whenmodified": "Fri, 06 Nov 2020 20:51:23 GMT"
    },
    {
        "rating": 2,
        "comment": "",
        "idprogram": "https://www.metacritic.com/tv/max-headroom",
        "whencreated": "Fri, 11 Dec 2020 10:55:55 GMT",
        "whenmodified": "Fri, 11 Dec 2020 10:55:55 GMT"
    },
    {
        "rating": 2,
        "comment": "",
        "idprogram": "https://www.metacritic.com/tv/mayans-mc",
        "whencreated": "Fri, 06 Nov 2020 23:39:14 GMT",
        "whenmodified": "Fri, 06 Nov 2020 23:39:14 GMT"
    },
    {
        "rating": 3,
        "comment": "",
        "idprogram": "https://www.metacritic.com/tv/mcmillions",
        "whencreated": "Thu, 12 Nov 2020 18:56:23 GMT",
        "whenmodified": "Thu, 12 Nov 2020 18:56:23 GMT"
    },
    {
        "rating": 2,
        "comment": "",
        "idprogram": "https://www.metacritic.com/tv/merlin",
        "whencreated": "Tue, 10 Nov 2020 17:27:09 GMT",
        "whenmodified": "Tue, 10 Nov 2020 17:27:09 GMT"
    },
    {
        "rating": 3,
        "comment": "",
        "idprogram": "https://www.metacritic.com/tv/millennium",
        "whencreated": "Fri, 06 Nov 2020 21:11:09 GMT",
        "whenmodified": "Fri, 06 Nov 2020 21:11:09 GMT"
    },
    {
        "rating": 2,
        "comment": "",
        "idprogram": "https://www.metacritic.com/tv/motherland-fort-salem",
        "whencreated": "Tue, 10 Nov 2020 09:47:55 GMT",
        "whenmodified": "Tue, 10 Nov 2020 09:47:55 GMT"
    },
    {
        "rating": 2,
        "comment": "",
        "idprogram": "https://www.metacritic.com/tv/mr-mercedes",
        "whencreated": "Fri, 06 Nov 2020 20:51:36 GMT",
        "whenmodified": "Fri, 06 Nov 2020 20:51:36 GMT"
    },
    {
        "rating": 3,
        "comment": "",
        "idprogram": "https://www.metacritic.com/tv/orphan-black",
        "whencreated": "Fri, 06 Nov 2020 20:51:52 GMT",
        "whenmodified": "Fri, 06 Nov 2020 20:51:52 GMT"
    },
    {
        "rating": 2,
        "comment": "",
        "idprogram": "https://www.metacritic.com/tv/our-flag-means-death",
        "whencreated": "Thu, 05 Jan 2023 16:38:28 GMT",
        "whenmodified": "Thu, 05 Jan 2023 16:38:28 GMT"
    },
    {
        "rating": 0,
        "comment": "",
        "idprogram": "https://www.metacritic.com/tv/outlander-2014",
        "whencreated": "Fri, 06 Nov 2020 20:51:55 GMT",
        "whenmodified": "Fri, 06 Nov 2020 20:51:55 GMT"
    },
    {
        "rating": 3,
        "comment": "",
        "idprogram": "https://www.metacritic.com/tv/peacemaker",
        "whencreated": "Thu, 24 Mar 2022 09:52:32 GMT",
        "whenmodified": "Tue, 10 Jan 2023 22:37:50 GMT"
    },
    {
        "rating": 3,
        "comment": "",
        "idprogram": "https://www.metacritic.com/tv/peaky-blinders",
        "whencreated": "Fri, 06 Nov 2020 20:52:08 GMT",
        "whenmodified": "Fri, 06 Nov 2020 20:52:08 GMT"
    },
    {
        "rating": 4,
        "comment": "",
        "idprogram": "https://www.metacritic.com/tv/person-of-interest",
        "whencreated": "Fri, 06 Nov 2020 21:05:21 GMT",
        "whenmodified": "Fri, 06 Nov 2020 21:05:21 GMT"
    },
    {
        "rating": 2,
        "comment": "",
        "idprogram": "https://www.metacritic.com/tv/powers",
        "whencreated": "Sat, 12 Mar 2022 15:48:58 GMT",
        "whenmodified": "Sat, 12 Mar 2022 15:48:58 GMT"
    },
    {
        "rating": 3,
        "comment": "",
        "idprogram": "https://www.metacritic.com/tv/prodigal-son",
        "whencreated": "Fri, 06 Nov 2020 21:01:21 GMT",
        "whenmodified": "Fri, 06 Nov 2020 21:01:21 GMT"
    },
    {
        "rating": 2,
        "comment": "",
        "idprogram": "https://www.metacritic.com/tv/project-blue-book",
        "whencreated": "Tue, 17 Nov 2020 10:53:47 GMT",
        "whenmodified": "Tue, 17 Nov 2020 10:53:47 GMT"
    },
    {
        "rating": 3,
        "comment": "",
        "idprogram": "https://www.metacritic.com/tv/pushing-daisies",
        "whencreated": "Fri, 06 Nov 2020 21:06:57 GMT",
        "whenmodified": "Fri, 06 Nov 2020 21:06:57 GMT"
    },
    {
        "rating": 2,
        "comment": "",
        "idprogram": "https://www.metacritic.com/tv/quantum-leap",
        "whencreated": "Fri, 06 Nov 2020 20:52:20 GMT",
        "whenmodified": "Fri, 06 Nov 2020 20:52:20 GMT"
    },
    {
        "rating": 3,
        "comment": "",
        "idprogram": "https://www.metacritic.com/tv/reaper",
        "whencreated": "Fri, 06 Nov 2020 21:00:14 GMT",
        "whenmodified": "Fri, 06 Nov 2020 21:00:14 GMT"
    },
    {
        "rating": 3,
        "comment": "",
        "idprogram": "https://www.metacritic.com/tv/red-dwarf",
        "whencreated": "Fri, 06 Nov 2020 20:52:31 GMT",
        "whenmodified": "Fri, 06 Nov 2020 23:28:52 GMT"
    },
    {
        "rating": 1,
        "comment": "",
        "idprogram": "https://www.metacritic.com/tv/reverie",
        "whencreated": "Sun, 30 Oct 2022 17:18:28 GMT",
        "whenmodified": "Sun, 30 Oct 2022 17:18:28 GMT"
    },
    {
        "rating": 3,
        "comment": "",
        "idprogram": "https://www.metacritic.com/tv/ripper-street",
        "whencreated": "Sun, 22 Nov 2020 14:24:44 GMT",
        "whenmodified": "Sun, 22 Nov 2020 14:24:44 GMT"
    },
    {
        "rating": 2,
        "comment": "",
        "idprogram": "https://www.metacritic.com/tv/robin-hood",
        "whencreated": "Fri, 01 Jan 2021 20:38:41 GMT",
        "whenmodified": "Fri, 01 Jan 2021 20:38:41 GMT"
    },
    {
        "rating": 2,
        "comment": "",
        "idprogram": "https://www.metacritic.com/tv/rome",
        "whencreated": "Fri, 06 Nov 2020 20:52:46 GMT",
        "whenmodified": "Fri, 06 Nov 2020 20:52:46 GMT"
    },
    {
        "rating": 2,
        "comment": "",
        "idprogram": "https://www.metacritic.com/tv/sanctuary",
        "whencreated": "Fri, 06 Nov 2020 20:53:09 GMT",
        "whenmodified": "Fri, 06 Nov 2020 20:53:09 GMT"
    },
    {
        "rating": 4,
        "comment": "",
        "idprogram": "https://www.metacritic.com/tv/shaun-the-sheep",
        "whencreated": "Fri, 06 Nov 2020 20:53:26 GMT",
        "whenmodified": "Fri, 06 Nov 2020 20:53:26 GMT"
    },
    {
        "rating": 2,
        "comment": "",
        "idprogram": "https://www.metacritic.com/tv/sherlock",
        "whencreated": "Fri, 06 Nov 2020 20:53:30 GMT",
        "whenmodified": "Fri, 06 Nov 2020 20:53:30 GMT"
    },
    {
        "rating": 1,
        "comment": "",
        "idprogram": "https://www.metacritic.com/tv/silent-witness",
        "whencreated": "Fri, 01 Jan 2021 20:37:35 GMT",
        "whenmodified": "Fri, 01 Jan 2021 20:37:35 GMT"
    },
    {
        "rating": 1,
        "comment": "",
        "idprogram": "https://www.metacritic.com/tv/slasher",
        "whencreated": "Sun, 08 Nov 2020 17:46:20 GMT",
        "whenmodified": "Sun, 08 Nov 2020 17:46:20 GMT"
    },
    {
        "rating": 3,
        "comment": "",
        "idprogram": "https://www.metacritic.com/tv/sons-of-anarchy",
        "whencreated": "Fri, 06 Nov 2020 23:38:49 GMT",
        "whenmodified": "Fri, 06 Nov 2020 23:38:49 GMT"
    },
    {
        "rating": 2,
        "comment": "",
        "idprogram": "https://www.metacritic.com/tv/spartacus-blood-and-sand",
        "whencreated": "Tue, 10 Nov 2020 17:28:37 GMT",
        "whenmodified": "Tue, 10 Nov 2020 17:28:37 GMT"
    },
    {
        "rating": 2,
        "comment": "",
        "idprogram": "https://www.metacritic.com/tv/spartacus-gods-of-the-arena",
        "whencreated": "Tue, 10 Nov 2020 17:37:01 GMT",
        "whenmodified": "Tue, 10 Nov 2020 17:37:01 GMT"
    },
    {
        "rating": 2,
        "comment": "",
        "idprogram": "https://www.metacritic.com/tv/spartacus-vengeance",
        "whencreated": "Tue, 10 Nov 2020 17:37:26 GMT",
        "whenmodified": "Tue, 10 Nov 2020 17:37:26 GMT"
    },
    {
        "rating": 2,
        "comment": "",
        "idprogram": "https://www.metacritic.com/tv/spartacus-war-of-the-damned",
        "whencreated": "Tue, 10 Nov 2020 17:37:39 GMT",
        "whenmodified": "Tue, 10 Nov 2020 17:37:39 GMT"
    },
    {
        "rating": 3,
        "comment": "",
        "idprogram": "https://www.metacritic.com/tv/stan-against-evil",
        "whencreated": "Fri, 20 Aug 2021 12:20:32 GMT",
        "whenmodified": "Fri, 20 Aug 2021 12:20:32 GMT"
    },
    {
        "rating": 3,
        "comment": "",
        "idprogram": "https://www.metacritic.com/tv/state-of-play",
        "whencreated": "Sat, 07 Nov 2020 00:20:53 GMT",
        "whenmodified": "Sat, 07 Nov 2020 00:20:53 GMT"
    },
    {
        "rating": 2,
        "comment": "",
        "idprogram": "https://www.metacritic.com/tv/stumptown",
        "whencreated": "Sun, 08 Nov 2020 20:53:36 GMT",
        "whenmodified": "Sun, 08 Nov 2020 20:53:36 GMT"
    },
    {
        "rating": 2,
        "comment": "",
        "idprogram": "https://www.metacritic.com/tv/taboo",
        "whencreated": "Fri, 06 Nov 2020 21:26:59 GMT",
        "whenmodified": "Fri, 06 Nov 2020 21:26:59 GMT"
    },
    {
        "rating": 2,
        "comment": "",
        "idprogram": "https://www.metacritic.com/tv/terminator-the-sarah-connor-chronicles",
        "whencreated": "Fri, 06 Nov 2020 21:26:27 GMT",
        "whenmodified": "Fri, 06 Nov 2020 21:26:27 GMT"
    },
    {
        "rating": 2,
        "comment": "",
        "idprogram": "https://www.metacritic.com/tv/the-blacklist",
        "whencreated": "Wed, 04 May 2022 16:19:54 GMT",
        "whenmodified": "Wed, 04 May 2022 16:19:54 GMT"
    },
    {
        "rating": 3,
        "comment": "",
        "idprogram": "https://www.metacritic.com/tv/the-capture",
        "whencreated": "Mon, 09 Nov 2020 15:45:54 GMT",
        "whenmodified": "Mon, 09 Nov 2020 15:45:54 GMT"
    },
    {
        "rating": 1,
        "comment": "",
        "idprogram": "https://www.metacritic.com/tv/the-event",
        "whencreated": "Fri, 16 Sep 2022 11:13:08 GMT",
        "whenmodified": "Fri, 16 Sep 2022 11:13:08 GMT"
    },
    {
        "rating": 2,
        "comment": "",
        "idprogram": "https://www.metacritic.com/tv/the-fall",
        "whencreated": "Fri, 06 Nov 2020 20:54:16 GMT",
        "whenmodified": "Fri, 06 Nov 2020 20:54:16 GMT"
    },
    {
        "rating": 3,
        "comment": "",
        "idprogram": "https://www.metacritic.com/tv/the-first",
        "whencreated": "Fri, 06 Nov 2020 23:50:14 GMT",
        "whenmodified": "Fri, 06 Nov 2020 23:50:14 GMT"
    },
    {
        "rating": 3,
        "comment": "",
        "idprogram": "https://www.metacritic.com/tv/the-fixer",
        "whencreated": "Sun, 08 Nov 2020 18:00:38 GMT",
        "whenmodified": "Sun, 08 Nov 2020 18:00:38 GMT"
    },
    {
        "rating": 2,
        "comment": "",
        "idprogram": "https://www.metacritic.com/tv/the-flash-2014",
        "whencreated": "Fri, 06 Nov 2020 20:54:19 GMT",
        "whenmodified": "Fri, 06 Nov 2020 20:54:19 GMT"
    },
    {
        "rating": 3,
        "comment": "",
        "idprogram": "https://www.metacritic.com/tv/the-following",
        "whencreated": "Sun, 13 Feb 2022 15:09:54 GMT",
        "whenmodified": "Sun, 13 Feb 2022 15:09:54 GMT"
    },
    {
        "rating": 2,
        "comment": "",
        "idprogram": "https://www.metacritic.com/tv/the-frankenstein-chronicles",
        "whencreated": "Wed, 02 Dec 2020 22:41:01 GMT",
        "whenmodified": "Wed, 02 Dec 2020 22:41:01 GMT"
    },
    {
        "rating": 3,
        "comment": "",
        "idprogram": "https://www.metacritic.com/tv/the-girl-before",
        "whencreated": "Wed, 04 May 2022 16:18:32 GMT",
        "whenmodified": "Wed, 04 May 2022 16:19:26 GMT"
    },
    {
        "rating": 4,
        "comment": "",
        "idprogram": "https://www.metacritic.com/tv/the-good-place",
        "whencreated": "Fri, 06 Nov 2020 20:57:07 GMT",
        "whenmodified": "Tue, 06 Apr 2021 15:16:06 GMT"
    },
    {
        "rating": 2,
        "comment": "",
        "idprogram": "https://www.metacritic.com/tv/the-handmaids-tale",
        "whencreated": "Fri, 06 Nov 2020 21:20:08 GMT",
        "whenmodified": "Fri, 06 Nov 2020 21:20:08 GMT"
    },
    {
        "rating": 2,
        "comment": "",
        "idprogram": "https://www.metacritic.com/tv/the-honorable-woman",
        "whencreated": "Fri, 01 Jan 2021 20:38:55 GMT",
        "whenmodified": "Fri, 01 Jan 2021 20:38:55 GMT"
    },
    {
        "rating": 2,
        "comment": "",
        "idprogram": "https://www.metacritic.com/tv/the-leftovers",
        "whencreated": "Fri, 06 Nov 2020 20:54:57 GMT",
        "whenmodified": "Fri, 06 Nov 2020 20:54:57 GMT"
    },
    {
        "rating": 1,
        "comment": "",
        "idprogram": "https://www.metacritic.com/tv/the-little-drummer-girl",
        "whencreated": "Tue, 10 Nov 2020 09:57:44 GMT",
        "whenmodified": "Tue, 10 Nov 2020 09:57:44 GMT"
    },
    {
        "rating": 3,
        "comment": "",
        "idprogram": "https://www.metacritic.com/tv/the-magicians-2016",
        "whencreated": "Fri, 06 Nov 2020 21:06:13 GMT",
        "whenmodified": "Fri, 06 Nov 2020 21:06:13 GMT"
    },
    {
        "rating": 2,
        "comment": "",
        "idprogram": "https://www.metacritic.com/tv/the-night-manager",
        "whencreated": "Fri, 06 Nov 2020 20:55:02 GMT",
        "whenmodified": "Fri, 06 Nov 2020 20:55:02 GMT"
    },
    {
        "rating": 2,
        "comment": "",
        "idprogram": "https://www.metacritic.com/tv/the-outpost",
        "whencreated": "Fri, 06 Nov 2020 21:04:22 GMT",
        "whenmodified": "Fri, 06 Nov 2020 21:04:22 GMT"
    },
    {
        "rating": 2,
        "comment": "",
        "idprogram": "https://www.metacritic.com/tv/the-passage",
        "whencreated": "Sun, 08 Nov 2020 17:43:34 GMT",
        "whenmodified": "Sun, 08 Nov 2020 17:43:34 GMT"
    },
    {
        "rating": 3,
        "comment": "",
        "idprogram": "https://www.metacritic.com/tv/the-returned",
        "whencreated": "Fri, 06 Nov 2020 20:55:19 GMT",
        "whenmodified": "Fri, 06 Nov 2020 20:55:19 GMT"
    },
    {
        "rating": 2,
        "comment": "",
        "idprogram": "https://www.metacritic.com/tv/the-rook",
        "whencreated": "Sun, 08 Nov 2020 17:42:54 GMT",
        "whenmodified": "Sun, 08 Nov 2020 17:42:54 GMT"
    },
    {
        "rating": 2,
        "comment": "",
        "idprogram": "https://www.metacritic.com/tv/the-shannara-chronicles",
        "whencreated": "Fri, 06 Nov 2020 23:55:55 GMT",
        "whenmodified": "Fri, 06 Nov 2020 23:55:55 GMT"
    },
    {
        "rating": 3,
        "comment": "",
        "idprogram": "https://www.metacritic.com/tv/the-simpsons",
        "whencreated": "Fri, 06 Nov 2020 20:55:25 GMT",
        "whenmodified": "Fri, 06 Nov 2020 20:55:25 GMT"
    },
    {
        "rating": 2,
        "comment": "",
        "idprogram": "https://www.metacritic.com/tv/the-strain",
        "whencreated": "Fri, 06 Nov 2020 20:56:08 GMT",
        "whenmodified": "Sun, 08 Nov 2020 17:52:44 GMT"
    },
    {
        "rating": 2,
        "comment": "",
        "idprogram": "https://www.metacritic.com/tv/the-terror",
        "whencreated": "Thu, 11 Mar 2021 14:44:03 GMT",
        "whenmodified": "Thu, 11 Mar 2021 14:44:03 GMT"
    },
    {
        "rating": 2,
        "comment": "",
        "idprogram": "https://www.metacritic.com/tv/the-unit",
        "whencreated": "Sun, 08 Nov 2020 17:41:20 GMT",
        "whenmodified": "Sun, 08 Nov 2020 17:41:20 GMT"
    },
    {
        "rating": 3,
        "comment": "",
        "idprogram": "https://www.metacritic.com/tv/the-vietnam-war",
        "whencreated": "Wed, 26 Jan 2022 22:39:46 GMT",
        "whenmodified": "Wed, 26 Jan 2022 22:39:46 GMT"
    },
    {
        "rating": 2,
        "comment": "",
        "idprogram": "https://www.metacritic.com/tv/the-vow-2020",
        "whencreated": "Thu, 12 Nov 2020 18:55:06 GMT",
        "whenmodified": "Thu, 12 Nov 2020 18:55:06 GMT"
    },
    {
        "rating": 2,
        "comment": "",
        "idprogram": "https://www.metacritic.com/tv/the-walking-dead",
        "whencreated": "Fri, 06 Nov 2020 20:56:18 GMT",
        "whenmodified": "Fri, 06 Nov 2020 20:56:18 GMT"
    },
    {
        "rating": 4,
        "comment": "",
        "idprogram": "https://www.metacritic.com/tv/the-wire",
        "whencreated": "Fri, 06 Nov 2020 20:56:20 GMT",
        "whenmodified": "Fri, 06 Nov 2020 20:56:20 GMT"
    },
    {
        "rating": 3,
        "comment": "",
        "idprogram": "https://www.metacritic.com/tv/the-x-files",
        "whencreated": "Fri, 06 Nov 2020 20:56:30 GMT",
        "whenmodified": "Fri, 06 Nov 2020 20:56:30 GMT"
    },
    {
        "rating": 2,
        "comment": "",
        "idprogram": "https://www.metacritic.com/tv/threshold",
        "whencreated": "Fri, 20 Nov 2020 09:58:54 GMT",
        "whenmodified": "Fri, 20 Nov 2020 09:58:54 GMT"
    },
    {
        "rating": 2,
        "comment": "",
        "idprogram": "https://www.metacritic.com/tv/top-of-the-lake",
        "whencreated": "Wed, 11 Nov 2020 12:03:26 GMT",
        "whenmodified": "Wed, 11 Nov 2020 12:03:26 GMT"
    },
    {
        "rating": 2,
        "comment": "",
        "idprogram": "https://www.metacritic.com/tv/torchwood-uk",
        "whencreated": "Fri, 06 Nov 2020 20:56:36 GMT",
        "whenmodified": "Fri, 06 Nov 2020 20:56:36 GMT"
    },
    {
        "rating": 2,
        "comment": "",
        "idprogram": "https://www.metacritic.com/tv/treadstone",
        "whencreated": "Wed, 26 Jan 2022 22:41:11 GMT",
        "whenmodified": "Wed, 26 Jan 2022 22:41:11 GMT"
    },
    {
        "rating": 2,
        "comment": "",
        "idprogram": "https://www.metacritic.com/tv/trickster",
        "whencreated": "Tue, 01 Dec 2020 23:07:23 GMT",
        "whenmodified": "Tue, 01 Dec 2020 23:07:23 GMT"
    },
    {
        "rating": 2,
        "comment": "",
        "idprogram": "https://www.metacritic.com/tv/true-blood",
        "whencreated": "Fri, 06 Nov 2020 20:56:41 GMT",
        "whenmodified": "Fri, 06 Nov 2020 20:56:41 GMT"
    },
    {
        "rating": 1,
        "comment": "",
        "idprogram": "https://www.metacritic.com/tv/under-the-dome",
        "whencreated": "Fri, 06 Nov 2020 20:56:45 GMT",
        "whenmodified": "Fri, 06 Nov 2020 20:56:45 GMT"
    },
    {
        "rating": 4,
        "comment": "",
        "idprogram": "https://www.metacritic.com/tv/unforgotten",
        "whencreated": "Fri, 06 Nov 2020 20:56:53 GMT",
        "whenmodified": "Fri, 06 Nov 2020 20:56:53 GMT"
    },
    {
        "rating": 2,
        "comment": "",
        "idprogram": "https://www.metacritic.com/tv/v",
        "whencreated": "Tue, 12 Jan 2021 09:55:49 GMT",
        "whenmodified": "Tue, 12 Jan 2021 09:55:49 GMT"
    },
    {
        "rating": 1,
        "comment": "",
        "idprogram": "https://www.metacritic.com/tv/v-the-series-1984",
        "whencreated": "Tue, 12 Jan 2021 09:55:34 GMT",
        "whenmodified": "Tue, 12 Jan 2021 09:55:34 GMT"
    },
    {
        "rating": 1,
        "comment": "",
        "idprogram": "https://www.metacritic.com/tv/vagrant-queen",
        "whencreated": "Fri, 20 Nov 2020 09:51:30 GMT",
        "whenmodified": "Fri, 20 Nov 2020 09:51:30 GMT"
    },
    {
        "rating": 3,
        "comment": "",
        "idprogram": "https://www.metacritic.com/tv/vienna-blood",
        "whencreated": "Thu, 19 Nov 2020 15:34:34 GMT",
        "whenmodified": "Sun, 19 Dec 2021 17:52:18 GMT"
    },
    {
        "rating": 3,
        "comment": "",
        "idprogram": "https://www.metacritic.com/tv/waking-the-dead",
        "whencreated": "Fri, 06 Nov 2020 23:48:27 GMT",
        "whenmodified": "Fri, 06 Nov 2020 23:48:27 GMT"
    },
    {
        "rating": 2,
        "comment": "",
        "idprogram": "https://www.metacritic.com/tv/warehouse-13",
        "whencreated": "Fri, 06 Nov 2020 20:57:17 GMT",
        "whenmodified": "Fri, 06 Nov 2020 20:57:17 GMT"
    },
    {
        "rating": 2,
        "comment": "",
        "idprogram": "https://www.metacritic.com/tv/watchmen-2019",
        "whencreated": "Wed, 03 Aug 2022 09:50:06 GMT",
        "whenmodified": "Wed, 03 Aug 2022 09:50:06 GMT"
    },
    {
        "rating": 3,
        "comment": "",
        "idprogram": "https://www.metacritic.com/tv/westworld",
        "whencreated": "Fri, 06 Nov 2020 20:57:21 GMT",
        "whenmodified": "Fri, 06 Nov 2020 20:57:21 GMT"
    },
    {
        "rating": 2,
        "comment": "",
        "idprogram": "https://www.metacritic.com/tv/z-nation",
        "whencreated": "Fri, 20 Nov 2020 09:57:26 GMT",
        "whenmodified": "Fri, 20 Nov 2020 09:57:26 GMT"
    }
]