[
    {
        "rating": 4,
        "comment": "",
        "idprogram": "https://www.metacritic.com/tv/30-rock",
        "whencreated": "Wed, 15 Nov 2017 22:46:09 GMT",
        "whenmodified": "Sun, 26 Jul 2020 15:49:43 GMT"
    },
    {
        "rating": 3,
        "comment": "",
        "idprogram": "https://www.metacritic.com/tv/archer",
        "whencreated": "Wed, 15 Nov 2017 22:46:14 GMT",
        "whenmodified": "Sun, 26 Jul 2020 15:49:43 GMT"
    },
    {
        "rating": 4,
        "comment": "",
        "idprogram": "https://www.metacritic.com/tv/arrested-development",
        "whencreated": "Wed, 15 Nov 2017 22:46:17 GMT",
        "whenmodified": "Sun, 26 Jul 2020 15:49:43 GMT"
    },
    {
        "rating": 3,
        "comment": "",
        "idprogram": "https://www.metacritic.com/tv/brooklyn-nine-nine",
        "whencreated": "Wed, 15 Nov 2017 22:46:25 GMT",
        "whenmodified": "Sun, 26 Jul 2020 15:49:43 GMT"
    },
    {
        "rating": 4,
        "comment": "",
        "idprogram": "https://www.metacritic.com/tv/curb-your-enthusiasm",
        "whencreated": "Wed, 15 Nov 2017 22:46:31 GMT",
        "whenmodified": "Sun, 26 Jul 2020 15:49:43 GMT"
    },
    {
        "rating": 3,
        "comment": "",
        "idprogram": "https://www.metacritic.com/tv/mad-men",
        "whencreated": "Wed, 15 Nov 2017 22:46:52 GMT",
        "whenmodified": "Sun, 26 Jul 2020 15:49:43 GMT"
    },
    {
        "rating": 2,
        "comment": "",
        "idprogram": "https://www.metacritic.com/tv/modern-family",
        "whencreated": "Wed, 15 Nov 2017 22:46:59 GMT",
        "whenmodified": "Sun, 26 Jul 2020 15:49:43 GMT"
    },
    {
        "rating": 1,
        "comment": "",
        "idprogram": "https://www.metacritic.com/tv/mr-robot",
        "whencreated": "Wed, 15 Nov 2017 22:47:03 GMT",
        "whenmodified": "Sun, 26 Jul 2020 15:49:43 GMT"
    },
    {
        "rating": 4,
        "comment": "",
        "idprogram": "https://www.metacritic.com/tv/seinfeld",
        "whencreated": "Wed, 15 Nov 2017 22:47:18 GMT",
        "whenmodified": "Sun, 26 Jul 2020 15:49:43 GMT"
    },
    {
        "rating": 4,
        "comment": "",
        "idprogram": "https://www.metacritic.com/tv/sherlock",
        "whencreated": "Wed, 15 Nov 2017 22:47:21 GMT",
        "whenmodified": "Sun, 26 Jul 2020 15:49:43 GMT"
    }
]