[
    {
        "rating": 2,
        "comment": "",
        "idprogram": "https://www.metacritic.com/tv/30-rock",
        "whencreated": "Mon, 21 Feb 2022 12:29:39 GMT",
        "whenmodified": "Mon, 21 Feb 2022 12:29:39 GMT"
    },
    {
        "rating": 2,
        "comment": "",
        "idprogram": "https://www.metacritic.com/tv/3rd-rock-from-the-sun",
        "whencreated": "Mon, 21 Feb 2022 12:29:43 GMT",
        "whenmodified": "Mon, 21 Feb 2022 12:29:43 GMT"
    },
    {
        "rating": 2,
        "comment": "",
        "idprogram": "https://www.metacritic.com/tv/angel",
        "whencreated": "Mon, 21 Feb 2022 12:29:31 GMT",
        "whenmodified": "Mon, 21 Feb 2022 12:29:32 GMT"
    },
    {
        "rating": 2,
        "comment": "",
        "idprogram": "https://www.metacritic.com/tv/anthony-bourdain-no-reservations",
        "whencreated": "Mon, 21 Feb 2022 12:29:53 GMT",
        "whenmodified": "Mon, 21 Feb 2022 12:29:53 GMT"
    },
    {
        "rating": 2,
        "comment": "",
        "idprogram": "https://www.metacritic.com/tv/avatar-the-last-airbender",
        "whencreated": "Mon, 21 Feb 2022 12:29:58 GMT",
        "whenmodified": "Mon, 21 Feb 2022 12:29:58 GMT"
    },
    {
        "rating": 2,
        "comment": "",
        "idprogram": "https://www.metacritic.com/tv/avatar-the-legend-of-korra",
        "whencreated": "Mon, 21 Feb 2022 12:30:01 GMT",
        "whenmodified": "Mon, 21 Feb 2022 12:30:01 GMT"
    },
    {
        "rating": 3,
        "comment": "",
        "idprogram": "https://www.metacritic.com/tv/sherlock",
        "whencreated": "Mon, 21 Feb 2022 12:45:34 GMT",
        "whenmodified": "Mon, 21 Feb 2022 12:45:34 GMT"
    }
]